leetcode/GQL_parse.py
leetcode/__init__.py
leetcode/config.yaml
leetcode/configuration.py
leetcode/content_markdown.py
leetcode/graphql_query.py
leetcode/leet_api.py
leetcode/loader.py
leetcode/main.py
leetcode/queries.graphql
leetcode/template.py
leetcode/models/__init__.py
leetcode/models/graphql_get_question_detail.py
leetcode/models/graphql_problemset_question_list.py
leetcode/models/graphql_question_content.py
leetcode/models/graphql_question_info_table.py
leetcode/models/graphql_question_of_today.py
leetcode/models/graphql_submission_list.py
leetcode/models/graphql_user_problems_solved.py
leetcode/models/problem_by_id_slug.py
leetcode/models/styles.py
leetcode/models/submit.py
tests/__init__.py
tests/test_check_session.py
tests/test_user_config.py
pyleetcode_cli-0.2.0.dist-info/LICENSE
pyleetcode_cli-0.2.0.dist-info/METADATA
pyleetcode_cli-0.2.0.dist-info/WHEEL
pyleetcode_cli-0.2.0.dist-info/entry_points.txt
pyleetcode_cli-0.2.0.dist-info/top_level.txt
pyleetcode_cli-0.2.0.dist-info/RECORD
