Metadata-Version: 2.1
Name: pyleetcode-cli
Version: 0.2.0
Summary: A CLI tool to access LeetCode
Home-page: https://github.com/Coderbeep/LeetCode-CLI
Author: Jakub Kubiak
Author-email: jakubkubiak234@gmail.com
License: MIT
License-File: LICENSE
